weightedcalcs/__init__.py
weightedcalcs/__version__.py
weightedcalcs/core.py
weightedcalcs-0.1.3.dist-info/LICENSE.txt
weightedcalcs-0.1.3.dist-info/METADATA
weightedcalcs-0.1.3.dist-info/WHEEL
weightedcalcs-0.1.3.dist-info/top_level.txt
weightedcalcs-0.1.3.dist-info/RECORD
